[
  {
    "full_name": "entityframeworktutorial/EF6-Code-First-Demo",
    "stargazers_count": 124,
    "open_issues_count": 0,
    "forks_count": 137
  },
  {
    "full_name": "csharpfritz/csharp_with_csharpfritz",
    "stargazers_count": 377,
    "open_issues_count": 8,
    "forks_count": 107
  },
  {
    "full_name": "moq/moq4",
    "stargazers_count": 4385,
    "open_issues_count": 36,
    "forks_count": 634
  },
  {
    "full_name": "markjprice/cs8dotnetcore3",
    "stargazers_count": 211,
    "open_issues_count": 4,
    "forks_count": 264
  },
  {
    "full_name": "MoienTajik/AspNetCore-Developer-Roadmap",
    "stargazers_count": 8346,
    "open_issues_count": 4,
    "forks_count": 1368
  },
  {
    "full_name": "hussien89aa/DataStructureAndAlgorithms",
    "stargazers_count": 614,
    "open_issues_count": 24,
    "forks_count": 2359
  },
  {
    "full_name": "sealedtx/java-youtube-downloader",
    "stargazers_count": 201,
    "open_issues_count": 7,
    "forks_count": 64
  },
  {
    "full_name": "SamyPesse/How-to-Make-a-Computer-Operating-System",
    "stargazers_count": 19681,
    "open_issues_count": 84,
    "forks_count": 3360
  },
  {
    "full_name": "geosolutions-it/geostore",
    "stargazers_count": 23,
    "open_issues_count": 49,
    "forks_count": 59
  },
  {
    "full_name": "jhu-ep-coursera/fullstack-course4",
    "stargazers_count": 6993,
    "open_issues_count": 4,
    "forks_count": 9559
  },
  {
    "full_name": "mohamedabotir/Teaching",
    "stargazers_count": 1,
    "open_issues_count": 0,
    "forks_count": 0
  },
  {
    "full_name": "DrWaleedAYousef/Teaching",
    "stargazers_count": 630,
    "open_issues_count": 0,
    "forks_count": 254
  },
  {
    "full_name": "ossu/computer-science",
    "stargazers_count": 104413,
    "open_issues_count": 10,
    "forks_count": 14333
  }
]